LuFeixuechengLinuxCongxiaoBaidaoDashenFix1/README.md
LuFeixuechengLinuxCongxiaoBaidaoDashenFix1/__init__.py
LuFeixuechengLinuxCongxiaoBaidaoDashenFix1/__main__.py
LuFeixuechengLinuxCongxiaoBaidaoDashenFix1/file.epub
LuFeixuechengLinuxCongxiaoBaidaoDashenFix1/index.html
LuFeixuechengLinuxCongxiaoBaidaoDashenFix1/css/__init__.py
LuFeixuechengLinuxCongxiaoBaidaoDashenFix1/css/annotations.css
LuFeixuechengLinuxCongxiaoBaidaoDashenFix1/css/main.css
LuFeixuechengLinuxCongxiaoBaidaoDashenFix1/css/normalize.css
LuFeixuechengLinuxCongxiaoBaidaoDashenFix1/css/popup.css
LuFeixuechengLinuxCongxiaoBaidaoDashenFix1/font/__init__.py
LuFeixuechengLinuxCongxiaoBaidaoDashenFix1/font/fontello.eot
LuFeixuechengLinuxCongxiaoBaidaoDashenFix1/font/fontello.svg
LuFeixuechengLinuxCongxiaoBaidaoDashenFix1/font/fontello.ttf
LuFeixuechengLinuxCongxiaoBaidaoDashenFix1/font/fontello.woff
LuFeixuechengLinuxCongxiaoBaidaoDashenFix1/img/__init__.py
LuFeixuechengLinuxCongxiaoBaidaoDashenFix1/img/annotator-glyph-sprite.png
LuFeixuechengLinuxCongxiaoBaidaoDashenFix1/img/annotator-icon-sprite.png
LuFeixuechengLinuxCongxiaoBaidaoDashenFix1/img/apple-touch-icon.png
LuFeixuechengLinuxCongxiaoBaidaoDashenFix1/img/cancelfullscreen.png
LuFeixuechengLinuxCongxiaoBaidaoDashenFix1/img/close.png
LuFeixuechengLinuxCongxiaoBaidaoDashenFix1/img/fullscreen.png
LuFeixuechengLinuxCongxiaoBaidaoDashenFix1/img/loader.gif
LuFeixuechengLinuxCongxiaoBaidaoDashenFix1/img/menu-icon.png
LuFeixuechengLinuxCongxiaoBaidaoDashenFix1/img/save.png
LuFeixuechengLinuxCongxiaoBaidaoDashenFix1/img/saved.png
LuFeixuechengLinuxCongxiaoBaidaoDashenFix1/img/settings-s.png
LuFeixuechengLinuxCongxiaoBaidaoDashenFix1/img/settings.png
LuFeixuechengLinuxCongxiaoBaidaoDashenFix1/img/star.png
LuFeixuechengLinuxCongxiaoBaidaoDashenFix1/js/__init__.py
LuFeixuechengLinuxCongxiaoBaidaoDashenFix1/js/epub.js
LuFeixuechengLinuxCongxiaoBaidaoDashenFix1/js/epub.min.js
LuFeixuechengLinuxCongxiaoBaidaoDashenFix1/js/epub.min.map
lu_feixuecheng_linux_congxiao_baidao_dashen_fix1-2025.3.25.1.dist-info/METADATA
lu_feixuecheng_linux_congxiao_baidao_dashen_fix1-2025.3.25.1.dist-info/WHEEL
lu_feixuecheng_linux_congxiao_baidao_dashen_fix1-2025.3.25.1.dist-info/entry_points.txt
lu_feixuecheng_linux_congxiao_baidao_dashen_fix1-2025.3.25.1.dist-info/top_level.txt
lu_feixuecheng_linux_congxiao_baidao_dashen_fix1-2025.3.25.1.dist-info/RECORD
